{"name":"build-javascript","namedChunkGroups":{"app":{"name":"app","assets":[{"name":"webpack-runtime-85aeda5fa15d8f768c96.js","size":4801},{"name":"framework-e1920fffb1cf79c01553.js","size":140793},{"name":"app-378573fd1288f9e0f70e.js","size":62513}],"filteredAssets":0,"assetsSize":208107,"filteredAuxiliaryAssets":3,"auxiliaryAssetsSize":603880},"component---src-pages-index-jsx":{"name":"component---src-pages-index-jsx","assets":[{"name":"styles.2bbf168fd233b4d479bc.css","size":226695},{"name":"component---src-pages-index-jsx-bfe3effb55d025fc6b53.js","size":16839}],"filteredAssets":0,"assetsSize":243534,"filteredAuxiliaryAssets":1,"auxiliaryAssetsSize":33580},"component---src-pages-sobre-jsx":{"name":"component---src-pages-sobre-jsx","assets":[{"name":"styles.2bbf168fd233b4d479bc.css","size":226695},{"name":"component---src-pages-sobre-jsx-eb24cc1ce8c25dd680a7.js","size":10660}],"filteredAssets":0,"assetsSize":237355,"filteredAuxiliaryAssets":1,"auxiliaryAssetsSize":18978},"component---src-pages-solucoes-jsx":{"name":"component---src-pages-solucoes-jsx","assets":[{"name":"styles.2bbf168fd233b4d479bc.css","size":226695},{"name":"component---src-pages-solucoes-jsx-1b12d8b9cd6effe0fac8.js","size":9775}],"filteredAssets":0,"assetsSize":236470,"filteredAuxiliaryAssets":1,"auxiliaryAssetsSize":18636}},"assetsByChunkName":{"app":["webpack-runtime-85aeda5fa15d8f768c96.js","framework-e1920fffb1cf79c01553.js","app-378573fd1288f9e0f70e.js"],"component---src-pages-index-jsx":["styles.2bbf168fd233b4d479bc.css","component---src-pages-index-jsx-bfe3effb55d025fc6b53.js"],"component---src-pages-sobre-jsx":["styles.2bbf168fd233b4d479bc.css","component---src-pages-sobre-jsx-eb24cc1ce8c25dd680a7.js"],"component---src-pages-solucoes-jsx":["styles.2bbf168fd233b4d479bc.css","component---src-pages-solucoes-jsx-1b12d8b9cd6effe0fac8.js"]},"childAssetsByChunkName":{}}